paymcp-0.8.3.dist-info/METADATA
paymcp-0.8.3.dist-info/WHEEL
paymcp-0.8.3.dist-info/entry_points.txt
paymcp-0.8.3.dist-info/licenses/LICENSE
paymcp/__init__.py
paymcp/core.py
paymcp/decorators.py
paymcp/payment/flows/__init__.py
paymcp/payment/flows/auto.py
paymcp/payment/flows/dynamic_tools.py
paymcp/payment/flows/elicitation.py
paymcp/payment/flows/oob.py
paymcp/payment/flows/progress.py
paymcp/payment/flows/resubmit.py
paymcp/payment/flows/state_utils.py
paymcp/payment/flows/two_step.py
paymcp/payment/flows/x402.py
paymcp/payment/payment_flow.py
paymcp/providers/__init__.py
paymcp/providers/adyen.py
paymcp/providers/base.py
paymcp/providers/coinbase.py
paymcp/providers/mock.py
paymcp/providers/paypal.py
paymcp/providers/square.py
paymcp/providers/stripe.py
paymcp/providers/walleot.py
paymcp/providers/x402.py
paymcp/state/__init__.py
paymcp/state/memory.py
paymcp/state/redis.py
paymcp/subscriptions/wrapper.py
paymcp/utils/context.py
paymcp/utils/crypto.py
paymcp/utils/disconnect.py
paymcp/utils/elicitation.py
paymcp/utils/jwt.py
paymcp/utils/messages.py
paymcp/utils/responseSchema.py
paymcp/utils/x402.py
paymcp-0.8.3.dist-info/RECORD
