Metadata-Version: 2.1
Name: paymcp
Version: 0.8.3
Summary: Provider-agnostic payment layer for MCP (Model Context Protocol) tools and agents.
Author-Email: PayMCP Open Source Contributors <dev@paymcp.info>
License: MIT
Requires-Python: >=3.10
Requires-Dist: requests>=2.32.4
Requires-Dist: pydantic>=2.11.7
Requires-Dist: cryptography>=46.0.3
